README.md
setup.py
circum_walabot/__init__.py
circum_walabot/walabot.py
circum_walabot.egg-info/PKG-INFO
circum_walabot.egg-info/SOURCES.txt
circum_walabot.egg-info/dependency_links.txt
circum_walabot.egg-info/entry_points.txt
circum_walabot.egg-info/requires.txt
circum_walabot.egg-info/top_level.txt