Metadata-Version: 2.1
Name: circum-walabot
Version: 0.0.4
Summary: Walabot sensor plugin for circum.
Home-page: https://github.com/LumineerLabs/circum-walabot
Author: Lane Haury
Author-email: lane@lumineerlabs.com
License: UNKNOWN
Platform: UNKNOWN
Classifier: License :: OSI Approved :: MIT License
Classifier: Programming Language :: Python
Classifier: Operating System :: OS Independent
Provides-Extra: lint
